marinetrafficapi/__init__.py
marinetrafficapi/bind.py
marinetrafficapi/client.py
marinetrafficapi/constants.py
marinetrafficapi/debug.py
marinetrafficapi/exceptions.py
marinetrafficapi/fields.py
marinetrafficapi/formatter.py
marinetrafficapi/models.py
marinetrafficapi/query_params.py
marinetrafficapi/response.py
marinetrafficapi/events/__init__.py
marinetrafficapi/events/client.py
marinetrafficapi/events/EV01_port_calls/__init__.py
marinetrafficapi/events/EV01_port_calls/models.py
marinetrafficapi/events/EV01_port_calls/query_params.py
marinetrafficapi/events/EV02_vessel_events/__init__.py
marinetrafficapi/events/EV02_vessel_events/models.py
marinetrafficapi/events/EV02_vessel_events/query_params.py
marinetrafficapi/events/EV03_berth_calls/__init__.py
marinetrafficapi/events/EV03_berth_calls/models.py
marinetrafficapi/events/EV03_berth_calls/query_params.py
marinetrafficapi/vessel_data/__init__.py
marinetrafficapi/vessel_data/client.py
marinetrafficapi/vessel_data/VD01_vessel_photos/__init__.py
marinetrafficapi/vessel_data/VD01_vessel_photos/models.py
marinetrafficapi/vessel_data/VD01_vessel_photos/query_params.py
marinetrafficapi/vessel_data/VD02_vessel_particulars/__init__.py
marinetrafficapi/vessel_data/VD02_vessel_particulars/models.py
marinetrafficapi/vessel_data/VD02_vessel_particulars/query_params.py
marinetrafficapi/vessel_data/VD03_search_vessel/__init__.py
marinetrafficapi/vessel_data/VD03_search_vessel/models.py
marinetrafficapi/vessel_data/VD03_search_vessel/query_params.py
marinetrafficapi/vessels_positions/__init__.py
marinetrafficapi/vessels_positions/client.py
marinetrafficapi/vessels_positions/PS01_vessel_historical_track/__init__.py
marinetrafficapi/vessels_positions/PS01_vessel_historical_track/models.py
marinetrafficapi/vessels_positions/PS01_vessel_historical_track/query_params.py
marinetrafficapi/vessels_positions/PS02_PS06_vessel_positions/__init__.py
marinetrafficapi/vessels_positions/PS02_PS06_vessel_positions/models.py
Marine_Traffic_API-0.20.1.dist-info/LICENSE
Marine_Traffic_API-0.20.1.dist-info/METADATA
Marine_Traffic_API-0.20.1.dist-info/WHEEL
Marine_Traffic_API-0.20.1.dist-info/top_level.txt
Marine_Traffic_API-0.20.1.dist-info/RECORD
