Metadata-Version: 2.1
Name: Marine Traffic API
Version: 0.20.1
Summary: Marine Traffic Client Api
Home-page: https://github.com/amphinicy/marine-traffic-client-api
Author: Ivan Arar @ Amphinicy Technologies
Author-email: ivan.arar@amphinicy.com
License: MIT
Project-URL: Source, https://github.com/amphinicy/marine-traffic-client-api
Keywords: marine traffic,api,cruise,distance,port,vessel,track,fleet
Platform: UNKNOWN
Classifier: Development Status :: 4 - Beta
Classifier: Intended Audience :: Developers
Classifier: Topic :: Software Development :: Build Tools
Classifier: License :: OSI Approved :: MIT License
Classifier: Programming Language :: Python :: 3.5
Classifier: Programming Language :: Python :: 3.6
Classifier: Programming Language :: Python :: 3.7
